wawebpy/__init__.py
wawebpy/_client.py
wawebpy/exceptions.py
wawebpy/structures/__init__.py
wawebpy/structures/_eventemitter.py
wawebpy/structures/_message.py
wawebpy/structures/auth/__init__.py
wawebpy/structures/auth/_baseauth.py
wawebpy/structures/auth/_legacysessionauth.py
wawebpy/structures/auth/_localauth.py
wawebpy/structures/auth/_noauth.py
wawebpy-0.0.1.dist-info/LICENSE
wawebpy-0.0.1.dist-info/METADATA
wawebpy-0.0.1.dist-info/WHEEL
wawebpy-0.0.1.dist-info/RECORD
