Metadata-Version: 2.3
Name: wawebpy
Version: 0.0.1
Summary: A Python library to control WhatsApp Web.
License: Apache
Author: Ulus Vatansever
Author-email: cvcvka5@gmail.com
Requires-Python: >=3.12
Classifier: License :: Other/Proprietary License
Classifier: Programming Language :: Python :: 3
Classifier: Programming Language :: Python :: 3.12
Classifier: Programming Language :: Python :: 3.13
Requires-Dist: playwright (>=1.40.0,<2.0.0)
Requires-Dist: qrcode (>=7.3,<8.0)
